pinecli.py
pinecone_cli-1.1.dist-info/LICENSE
pinecone_cli-1.1.dist-info/METADATA
pinecone_cli-1.1.dist-info/WHEEL
pinecone_cli-1.1.dist-info/entry_points.txt
pinecone_cli-1.1.dist-info/top_level.txt
pinecone_cli-1.1.dist-info/zip-safe
pinecone_cli-1.1.dist-info/RECORD
